fastapi_launchpad/__init__.py
fastapi_launchpad/cli.py
fastapi_launchpad/templates.py
fastapi_launchpad/utils.py
fastapi_launchpad-0.1.0.dist-info/METADATA
fastapi_launchpad-0.1.0.dist-info/WHEEL
fastapi_launchpad-0.1.0.dist-info/entry_points.txt
fastapi_launchpad-0.1.0.dist-info/licenses/LICENSE
fastapi_launchpad-0.1.0.dist-info/RECORD
