Metadata-Version: 2.4
Name: fastapi-launchpad
Version: 0.1.0
Summary: A CLI tool to quickly scaffold FastAPI projects
Project-URL: Homepage, https://github.com/talhajamil05/fastapi-launchpad
Project-URL: Documentation, https://github.com/talhajamil05/fastapi-launchpad#readme
Project-URL: Issues, https://github.com/talhajamil05/fastapi-launchpad/issues
Project-URL: Source, https://github.com/talhajamil05/fastapi-launchpad
Author-email: Talha Jamil <t.jamil05@gmail.com>
License: MIT License
License-File: LICENSE
Keywords: boilerplate,cli,fastapi,scaffold,starter,template
Classifier: Development Status :: 3 - Alpha
Classifier: Intended Audience :: Developers
Classifier: License :: OSI Approved :: MIT License
Classifier: Programming Language :: Python :: 3
Classifier: Programming Language :: Python :: 3.8
Classifier: Programming Language :: Python :: 3.9
Classifier: Programming Language :: Python :: 3.10
Classifier: Programming Language :: Python :: 3.11
Classifier: Programming Language :: Python :: 3.12
Requires-Python: >=3.8
Requires-Dist: fastapi>=0.100.0
Requires-Dist: python-dotenv>=1.0.0
Requires-Dist: rich>=13.0.0
Requires-Dist: typer>=0.9.0
Requires-Dist: uvicorn>=0.22.0
Provides-Extra: dev
Requires-Dist: mypy>=1.5.0; extra == 'dev'
Requires-Dist: pytest-cov>=4.0; extra == 'dev'
Requires-Dist: pytest>=7.0; extra == 'dev'
Requires-Dist: ruff>=0.3.0; extra == 'dev'
Requires-Dist: typer[all]>=0.9.0; extra == 'dev'
